clickhouse_orm/__init__.py
clickhouse_orm/database.py
clickhouse_orm/engines.py
clickhouse_orm/fields.py
clickhouse_orm/funcs.py
clickhouse_orm/migrations.py
clickhouse_orm/models.py
clickhouse_orm/query.py
clickhouse_orm/system_models.py
clickhouse_orm/utils.py
clickhouse_orm-2.2.2.dist-info/LICENSE
clickhouse_orm-2.2.2.dist-info/WHEEL
clickhouse_orm-2.2.2.dist-info/METADATA
clickhouse_orm-2.2.2.dist-info/RECORD
