Metadata-Version: 2.1
Name: clickhouse-orm
Version: 2.2.2
Summary: A simple ORM for working with the Clickhouse database. Maintainance fork of infi.clickhouse_orm.
Home-page: https://github.com/SuadeLabs/clickhouse_orm
License: BSD
Author: olliemath
Author-email: oliver.margetts@gmail.com
Requires-Python: >=3.6.2,<4
Classifier: Intended Audience :: Developers
Classifier: Intended Audience :: System Administrators
Classifier: License :: OSI Approved :: BSD License
Classifier: License :: Other/Proprietary License
Classifier: Operating System :: OS Independent
Classifier: Programming Language :: Python
Classifier: Programming Language :: Python :: 3
Classifier: Programming Language :: Python :: 3.6
Classifier: Programming Language :: Python :: 3.7
Classifier: Programming Language :: Python :: 3.8
Classifier: Programming Language :: Python :: 3.9
Classifier: Topic :: Database
Classifier: Topic :: Software Development :: Libraries :: Python Modules
Requires-Dist: iso8601
Requires-Dist: pytz
Requires-Dist: requests
Project-URL: Repository, https://github.com/SuadeLabs/clickhouse_orm
